Metadata-Version: 1.1
Name: GBRestructure
Version: 0.4.0
Summary: A CLI tool to help with multi-team Git branching strategies
Home-page: UNKNOWN
Author: Josh Fischer
Author-email: josh@joshfischer.io
License: Apache
Platform: UNKNOWN
Classifier: Development Status :: 4 - Beta
Classifier: License :: OSI Approved :: Apache Software License
Classifier: Programming Language :: Python :: 2.7
Classifier: Topic :: Software Development :: Version Control
